{"id":"2eb7w5pgXFU","url":"https://www.youtube.com/watch?v=2eb7w5pgXFU","embed":{"iframeUrl":"https://www.youtube.com/embed/2eb7w5pgXFU","flashUrl":"http://www.youtube.com/v/2eb7w5pgXFU?version=3&autohide=1","width":1280,"height":720,"flashSecureUrl":"https://www.youtube.com/v/2eb7w5pgXFU?version=3&autohide=1"},"duration":3386,"title":"10 глупых вопросов физику-теоретику 💥   🔥 🔴  ★ 👍 наука✔\"Катющик ТВ\"","description":"Поддержать канал и выход новых роликов: https://boosty.to/tribunal100\n#наука, #физика, #научный метод, #наука и техника, #вселенная, физика простым языком, \nАвтор музыки  !!!!! Глиняный идол!!!!\nфизика доступно,\nформулы, графики (монография) здесь:\nhttp://vk.com/doc-62147854_245217232\nПоддержать выпуск новых видео:\nкарта сбербанка: 5469310022484378 \nлибо по номеру: +79095256043 \nQIWI кошелёк +7 9095256043 \nPayPal kat_vic@mail.ru \nЮ money 5106218038886388","best_video":{"mimeType":"video/mp4; codecs=\"avc1.640028\"","contentLength":346859516,"size":"331MB","url":"https://rr2---sn-xn5ucu-q0cs.googlevideo.com/videoplayback?expire=1676879847&ei=h9PyY_jLJIOBmQbonaiYCQ&ip=78.16.131.161&id=o-AFjPXB7rLCjHZnz69q8orNvp2hUAAaGkrUVXJv-VYjjK&itag=137&aitags=133%2C134%2C135%2C136%2C137%2C160%2C242%2C243%2C244%2C247%2C248%2C278&source=youtube&requiressl=yes&mh=T9&mm=31%2C29&mn=sn-xn5ucu-q0cs%2Csn-q0cedn7s&ms=au%2Crdu&mv=m&mvi=2&pl=21&initcwndbps=2066250&vprv=1&mime=video%2Fmp4&ns=rsdGSPPhT-Ho4xRh7V7sE14L&gir=yes&clen=346859516&dur=3385.280&lmt=1670721968903916&mt=1676857978&fvip=5&keepalive=yes&fexp=24007246&beids=24472435&c=WEB&txp=4432434&n=1UetQuN24KjYlg&sparams=expire%2Cei%2Cip%2Cid%2Caitags%2Csource%2Crequiressl%2Cvprv%2Cmime%2Cns%2Cgir%2Cclen%2Cdur%2Clmt&sig=AOq0QJ8wRgIhAJxXexJqNAWP9GnjiGMpIIxBzZ8wSRooJfrzuKtu6euhAiEAtuF-r3BRQe95Cu5OAvd7l2dBNNJzviG5Eb6IfBkHMMI%3D&lsparams=mh%2Cmm%2Cmn%2Cms%2Cmv%2Cmvi%2Cpl%2Cinitcwndbps&lsig=AG3C_xAwRgIhAOlFcBns-l_daOJ-GXc7ZiFgjBgG9EFWjawOCYwvd2XPAiEA0zaOLgZuGANQBJWqvJqF3t7Eel76KkP9mHXYJdsM0Bg%3D","fps":25,"width":1920,"height":1080},"worst_video":{"mimeType":"video/mp4; codecs=\"avc1.4d400c\"","contentLength":9109557,"size":"9MB","url":"https://rr2---sn-xn5ucu-q0cs.googlevideo.com/videoplayback?expire=1676879847&ei=h9PyY_jLJIOBmQbonaiYCQ&ip=78.16.131.161&id=o-AFjPXB7rLCjHZnz69q8orNvp2hUAAaGkrUVXJv-VYjjK&itag=160&aitags=133%2C134%2C135%2C136%2C137%2C160%2C242%2C243%2C244%2C247%2C248%2C278&source=youtube&requiressl=yes&mh=T9&mm=31%2C29&mn=sn-xn5ucu-q0cs%2Csn-q0cedn7s&ms=au%2Crdu&mv=m&mvi=2&pl=21&initcwndbps=2066250&vprv=1&mime=video%2Fmp4&ns=rsdGSPPhT-Ho4xRh7V7sE14L&gir=yes&clen=9109557&dur=3385.280&lmt=1670721954688880&mt=1676857978&fvip=5&keepalive=yes&fexp=24007246&beids=24472435&c=WEB&txp=4432434&n=1UetQuN24KjYlg&sparams=expire%2Cei%2Cip%2Cid%2Caitags%2Csource%2Crequiressl%2Cvprv%2Cmime%2Cns%2Cgir%2Cclen%2Cdur%2Clmt&sig=AOq0QJ8wRAIgJjy4pklkXV42UudSwMbXo02euHNOA6AhbLRB5bCn-qkCIHBMBTKhH8CbvDDT6fvVGwDt2pUg4pP9iXKh9MJpeNY2&lsparams=mh%2Cmm%2Cmn%2Cms%2Cmv%2Cmvi%2Cpl%2Cinitcwndbps&lsig=AG3C_xAwRgIhAOlFcBns-l_daOJ-GXc7ZiFgjBgG9EFWjawOCYwvd2XPAiEA0zaOLgZuGANQBJWqvJqF3t7Eel76KkP9mHXYJdsM0Bg%3D","fps":25,"width":256,"height":144},"worst_audio":{"mimeType":"audio/mp4; codecs=\"mp4a.40.2\"","contentLength":54788561,"size":"52MB","url":"https://rr2---sn-xn5ucu-q0cs.googlevideo.com/videoplayback?expire=1676879847&ei=h9PyY_jLJIOBmQbonaiYCQ&ip=78.16.131.161&id=o-AFjPXB7rLCjHZnz69q8orNvp2hUAAaGkrUVXJv-VYjjK&itag=140&source=youtube&requiressl=yes&mh=T9&mm=31%2C29&mn=sn-xn5ucu-q0cs%2Csn-q0cedn7s&ms=au%2Crdu&mv=m&mvi=2&pl=21&initcwndbps=2066250&vprv=1&mime=audio%2Fmp4&ns=rsdGSPPhT-Ho4xRh7V7sE14L&gir=yes&clen=54788561&dur=3385.329&lmt=1670721219585041&mt=1676857978&fvip=5&keepalive=yes&fexp=24007246&beids=24472435&c=WEB&txp=4432434&n=1UetQuN24KjYlg&sparams=expire%2Cei%2Cip%2Cid%2Citag%2Csource%2Crequiressl%2Cvprv%2Cmime%2Cns%2Cgir%2Cclen%2Cdur%2Clmt&sig=AOq0QJ8wRQIhAOMsOhNJ37LS0nJRhq_rU-Tuk9DH_j3Ihjn-okKC-n3jAiA9_ayHMhjQh93lh6rdnAQzPSmuiesJWQPb8K0eleULXA%3D%3D&lsparams=mh%2Cmm%2Cmn%2Cms%2Cmv%2Cmvi%2Cpl%2Cinitcwndbps&lsig=AG3C_xAwRgIhAOlFcBns-l_daOJ-GXc7ZiFgjBgG9EFWjawOCYwvd2XPAiEA0zaOLgZuGANQBJWqvJqF3t7Eel76KkP9mHXYJdsM0Bg%3D","audioBitrate":128}}