[{"start":"4.97","dur":"4.57","text":"привет бумстартер"},{"start":"6.839","dur":"6.901","text":"я виктор катющик представляю видео"},{"start":"9.54","dur":"6.9","text":"проект научный трибунов мы снимаем"},{"start":"13.74","dur":"5.76","text":"фильмы по самым важным для человека тема"},{"start":"16.44","dur":"5.72","text":"и даем информацию которую невозможно"},{"start":"19.5","dur":"6.96","text":"получить не из какого другого источника"},{"start":"22.16","dur":"6.279","text":"совсем не из какого только у нас тем на"},{"start":"26.46","dur":"3.899","text":"фильмов настолько интересно что вы"},{"start":"28.439","dur":"5.811","text":"оставляете отзывы"},{"start":"30.359","dur":"7.681","text":"которые даже неловко произносить вслух"},{"start":"34.25","dur":"6.969","text":"это настолько захватывающе что матрица 1"},{"start":"38.04","dur":"4.949","text":"так интеллигентно ложатся в обморок за"},{"start":"41.219","dur":"5.491","text":"выражение смотрю в монитор"},{"start":"42.989","dur":"6.361","text":"совершенно ошеломлён самый лучший фильм"},{"start":"46.71","dur":"3.09","text":"о мироздании и политики что довелось"},{"start":"49.35","dur":"3.63","text":"видеть"},{"start":"49.8","dur":"6.09","text":"почему вам стало так интересно именно на"},{"start":"52.98","dur":"6.27","text":"нашем канале потому что для вашего мозга"},{"start":"55.89","dur":"6.149","text":"вы делаем всего и считаем медведей в"},{"start":"59.25","dur":"6.659","text":"арктике и протыкаем селедку и даже"},{"start":"62.039","dur":"6.091","text":"сжигаем чучело хокинга игра мамы 1 кто"},{"start":"65.909","dur":"5.28","text":"начал давать только сто процентов"},{"start":"68.13","dur":"4.83","text":"научно состоятельного информацию научно"},{"start":"71.189","dur":"4.641","text":"подтвержденную информацию"},{"start":"72.96","dur":"5.36","text":"свободную от какой-либо научные буду"},{"start":"75.83","dur":"5.02","text":"фальсификаций сыр гипотез и"},{"start":"78.32","dur":"6.159","text":"корпоративных интересов только"},{"start":"80.85","dur":"6.449","text":"проверенные факты мы открыто говорим где"},{"start":"84.479","dur":"5.82","text":"информация достоверна а где ученые"},{"start":"87.299","dur":"5.941","text":"немножко приврали и истинное лицо"},{"start":"90.299","dur":"6.39","text":"легитимные науки повергают многих из вас"},{"start":"93.24","dur":"6.54","text":"шок вы постоянно требуются новые фильмы"},{"start":"96.689","dur":"5.191","text":"и их надо снимать но средств на это"},{"start":"99.78","dur":"5.25","text":"реально не хватает недостаток"},{"start":"101.88","dur":"5.01","text":"оборудования и других ресурсов вы уже"},{"start":"105.03","dur":"4.199","text":"предлагали подержать про их на моем"},{"start":"106.89","dur":"3.96","text":"ставьте ли но пока имелись внутренние"},{"start":"109.229","dur":"4.561","text":"резервы мы не откликались"},{"start":"110.85","dur":"4.68","text":"и просто работали но сегодня мы здесь и"},{"start":"113.79","dur":"4.77","text":"давайте уже снимают фильмы"},{"start":"115.53","dur":"6.21","text":"общими силами есть хороший повод"},{"start":"118.56","dur":"6","text":"снять новый фильм фильм повышающие"},{"start":"121.74","dur":"4.309","text":"мыслительные способности человека за 1"},{"start":"124.56","dur":"4.35","text":"просмотр"},{"start":"126.049","dur":"5.921","text":"усовершенствование мозга об греть мозга"},{"start":"128.91","dur":"6.15","text":"фильм по логике мышления и научному"},{"start":"131.97","dur":"5.58","text":"методу как это будет выглядеть в"},{"start":"135.06","dur":"5.67","text":"результате уже примерно догадываетесь ли"},{"start":"137.55","dur":"5.7","text":"будет интересно ну а если вы только что"},{"start":"140.73","dur":"5.39","text":"присоединились еще не представляете как"},{"start":"143.25","dur":"6.48","text":"это работает просто зайдите на наш канал"},{"start":"146.12","dur":"5.73","text":"подключитесь будет незабываемым но"},{"start":"149.73","dur":"4.68","text":"должен предупредить что это опасно"},{"start":"151.85","dur":"3.19","text":"качество информации действует как"},{"start":"154.41","dur":"3.27","text":"наркотик"},{"start":"155.04","dur":"5.22","text":"вы один раз подсаживаетесь и мост"},{"start":"157.68","dur":"4.35","text":"требует еще и еще все фильмы"},{"start":"160.26","dur":"3.75","text":"выкладываются свободный доступ и"},{"start":"162.03","dur":"3","text":"моментально разносятся по интернету"},{"start":"164.01","dur":"3.54","text":"множество ссылок"},{"start":"165.03","dur":"5.64","text":"среди наших зрителей и читателей"},{"start":"167.55","dur":"5.85","text":"академические учреждения университеты и"},{"start":"170.67","dur":"5.4","text":"просто люди на которых это очень важно"},{"start":"173.4","dur":"6.03","text":"многие к нам приходят как на работу и"},{"start":"176.07","dur":"5.67","text":"оставляю все свое время каждый день с 8"},{"start":"179.43","dur":"3.33","text":"утра по многу страниц в день прямо из"},{"start":"181.74","dur":"5.46","text":"институтов ран"},{"start":"182.76","dur":"5.4","text":"ну как страшно если нет стартует снимаем"},{"start":"187.2","dur":"3.89","text":"классное кино"},{"start":"188.16","dur":"2.93","text":"of great мозга"},{"start":"194.78","dur":"4.65","text":"благодарю за внимание"},{"start":"196.59","dur":"2.84","text":"подключайтесь"}]