[{"start":"0","dur":"4.339","text":"вот есть два мировоззрения есть"},{"start":"2.7","dur":"5.159","text":"мировоззрение казачьи"},{"start":"4.339","dur":"10.09","text":"из мировоззрение холопской а чем они"},{"start":"7.859","dur":"10.651","text":"отличаются друг от друга от холоп как он"},{"start":"14.429","dur":"5.751","text":"себе представляет миропонимание холопа и"},{"start":"18.51","dur":"13.47","text":"миропонимания казарка"},{"start":"20.18","dur":"16.05","text":"чем отличаются вот народ украины откуда"},{"start":"31.98","dur":"4.25","text":"он взялся были казаки были холопы"},{"start":"41.12","dur":"15","text":"кто на казаков работал у казака были"},{"start":"53.46","dur":"5.669","text":"батраки свои"},{"start":"56.12","dur":"5.189","text":"вы об этом не знаете нет не знаете что у"},{"start":"59.129","dur":"5.541","text":"казаков были батраки"},{"start":"61.309","dur":"12.701","text":"что рядом с казаками жили мастеровые"},{"start":"64.67","dur":"11.32","text":"которые не были казаками вот шевченко"},{"start":"74.01","dur":"8.94","text":"фамилия это казачьи или холопской а"},{"start":"75.99","dur":"9.11","text":"фамилия шевченко это человек который шил"},{"start":"82.95","dur":"2.15","text":"обувь"},{"start":"87.08","dur":"6.13","text":"эта профессия невский вот именно вот"},{"start":"90.619","dur":"5.221","text":"принесенный казак и казак это разные"},{"start":"93.21","dur":"5.67","text":"люди ведут я"},{"start":"95.84","dur":"6.43","text":"мировоззрение к закону к чему сводится в"},{"start":"98.88","dur":"16.37","text":"чем заключается взаимоотношения казака с"},{"start":"102.27","dur":"12.98","text":"миром исторические"},{"start":"122.03","dur":"6.839","text":"в свободное от войны и время"},{"start":"125.04","dur":"7.05","text":"от военных действий занимались ремеслом"},{"start":"128.869","dur":"8.531","text":"подковы ковал кто-то там землю пахал но"},{"start":"132.09","dur":"9.39","text":"как только газа газа"},{"start":"137.4","dur":"12.38","text":"мог делать все но менять мировоззрение"},{"start":"141.48","dur":"22.62","text":"казака в чем заключается образование"},{"start":"149.78","dur":"16.38","text":"области вот есть казаки есть казачье"},{"start":"164.1","dur":"7.47","text":"войско"},{"start":"166.16","dur":"12.79","text":"войска дает казаку землю вот коза джим"},{"start":"171.57","dur":"10.11","text":"живет на земле войск где казачья земля"},{"start":"178.95","dur":"4.289","text":"находится вот есть частная земля"},{"start":"181.68","dur":"5.33","text":"которому господа"},{"start":"183.239","dur":"7.261","text":"out вообще казачья земля где находится"},{"start":"187.01","dur":"4.12","text":"откуда докуда коза часть казачьи земли"},{"start":"190.5","dur":"4.98","text":"где"},{"start":"191.13","dur":"17.22","text":"на земном шаре где расположены казачьи"},{"start":"195.48","dur":"18.479","text":"земли да то есть а казачье войско у нас"},{"start":"208.35","dur":"8.6","text":"было где от одного моля то другого от"},{"start":"213.959","dur":"12.651","text":"западного до восточного"},{"start":"216.95","dur":"9.66","text":"это все казачьи земли балтики"},{"start":"229.87","dur":"12.99","text":"шеи и прибалтийские страны то сколько ли"},{"start":"232.239","dur":"14.911","text":"каддафи естественно ну понятно потому"},{"start":"242.86","dur":"7.65","text":"что они ушли в как католичество поэтому"},{"start":"247.15","dur":"6.119","text":"бы начали рубиться между собой ада и"},{"start":"250.51","dur":"6.53","text":"этого когда католические игры не"},{"start":"253.269","dur":"6.421","text":"начались это была одна"},{"start":"257.04","dur":"7.379","text":"один массив народа включал себя и"},{"start":"259.69","dur":"9.03","text":"поляков и малороссов"},{"start":"264.419","dur":"8.671","text":"пермских и все остальные национальности"},{"start":"268.72","dur":"4.37","text":"только тут я сказал некорректно он"},{"start":"277.11","dur":"44.559","text":"великорусские и welicoruss это разное"},{"start":"279.76","dur":"48.029","text":"понятие по сути дела куда расселение"},{"start":"321.669","dur":"9.921","text":"кому куда расселение руку на силился"},{"start":"327.789","dur":"3.801","text":"удивите меня еще раз"},{"start":"333.44","dur":"12.2","text":"например сказать приходили например на"},{"start":"341.48","dur":"6.87","text":"юге тут же ряду у нас сейчас украина"},{"start":"345.64","dur":"23.46","text":"естественно происходил ассимиляции это"},{"start":"348.35","dur":"24.12","text":"понятно 0 и расселение кого куда еще раз"},{"start":"369.1","dur":"7.59","text":"вам кажется что люди тусовались или была"},{"start":"372.47","dur":"4.22","text":"какая то тенденция кто-то куда-то ехал"},{"start":"379.81","dur":"6.58","text":"грубо говоря если вы не знаете что ту"},{"start":"382.52","dur":"6","text":"куда-куда кто конкретно ехал значит вас"},{"start":"386.39","dur":"9.06","text":"обманули никто никуда не ехал все"},{"start":"388.52","dur":"17.39","text":"нормально сейчас проживает сейчас"},{"start":"395.45","dur":"10.46","text":"проживаю вот вы находитесь в центре"},{"start":"406.419","dur":"7.171","text":"украина + польша плюс белоруссия плюс"},{"start":"412.04","dur":"6.71","text":"россии"},{"start":"413.59","dur":"10.24","text":"плюс балтика брю швеция"},{"start":"418.75","dur":"9.28","text":"плюс финляндия вот это вот практически"},{"start":"423.83","dur":"9.95","text":"один и тот же от нас все вместе которые"},{"start":"428.03","dur":"11.63","text":"был здесь всегда любят atmos гонял по"},{"start":"433.78","dur":"5.88","text":"остальным материкам и ровнял всё везде"},{"start":"443.76","dur":"10.19","text":"я честно говоря не до конца понимаю вы"},{"start":"446.64","dur":"14.46","text":"говорите потому что изначально эти 100"},{"start":"453.95","dur":"9.04","text":"настоящий времен как происходило со мной"},{"start":"461.1","dur":"5.64","text":"изначально когда тысяч лет назад"},{"start":"462.99","dur":"9.63","text":"происходило ну вот подождите вот скиф вы"},{"start":"466.74","dur":"9.21","text":"знаете кто такие вот скажем древние"},{"start":"472.62","dur":"6.99","text":"племена которая жили по территории всей"},{"start":"475.95","dur":"8.91","text":"евразии они имеют ту же саму гаплогруппу"},{"start":"479.61","dur":"10.2","text":"с той средний украинец украинские коровы"},{"start":"484.86","dur":"7.28","text":"бродят по индии генетика схожие вот эти"},{"start":"489.81","dur":"4.59","text":"вот горбатые индийские коровы имеют"},{"start":"492.14","dur":"5.62","text":"непохожие на украинских имеет ту же"},{"start":"494.4","dur":"6.72","text":"самую генетику что украинские коровы что"},{"start":"497.76","dur":"7.1","text":"на средней полосе россии коровы вот одна"},{"start":"501.12","dur":"8.66","text":"генетика у них и у индейских коров"},{"start":"504.86","dur":"4.92","text":"верхняя карта и энди из индейцев"},{"start":"510.53","dur":"10.139","text":"имеют ту же гаплогруппу что украина что"},{"start":"514.44","dur":"10.61","text":"россия что польша это один народ который"},{"start":"520.669","dur":"4.381","text":"тусовался здесь"},{"start":"526.17","dur":"5.52","text":"ладно народ"},{"start":"529.47","dur":"4.559","text":"но о влиянии то есть наше внешнее"},{"start":"531.69","dur":"4.53","text":"различие какие-то не значить какие"},{"start":"534.029","dur":"7.141","text":"различия кто он сказал что есть какие-то"},{"start":"536.22","dur":"11.19","text":"различия во всех по и мистически внешнее"},{"start":"541.17","dur":"9.06","text":"различие от украинского народа подождите"},{"start":"547.41","dur":"6.63","text":"подождите индийский народ это отдельно я"},{"start":"550.23","dur":"5.82","text":"говорю про верхние карты про различие вы"},{"start":"554.04","dur":"4.26","text":"мне скажете различие между поляком"},{"start":"556.05","dur":"3.589","text":"русским украинцам белорусам вы можете"},{"start":"558.3","dur":"6.63","text":"найти"},{"start":"559.639","dur":"7.421","text":"нет мы один народ но ментальность это"},{"start":"564.93","dur":"2.82","text":"вот вас отрабатывают у вас западная"},{"start":"567.06","dur":"3.149","text":"ментальность"},{"start":"567.75","dur":"10.67","text":"в других телевизоров другая ментальность"},{"start":"570.209","dur":"8.211","text":"поля к встрече это искусственный процесс"},{"start":"578.54","dur":"6.39","text":"таком мировоззрение холопа чем"},{"start":"581.01","dur":"3.92","text":"отличается от мировоззрения казака"},{"start":"587.36","dur":"23.669","text":"где земля казака клуб и земля от одного"},{"start":"608.82","dur":"7.019","text":"океана до другого"},{"start":"611.029","dur":"8.401","text":"казачьему иска везде где есть казачьего"},{"start":"615.839","dur":"7.051","text":"войска там его земля там казак пределе"},{"start":"619.43","dur":"7.659","text":"мировоззрение холопа там где хорошо"},{"start":"622.89","dur":"6.78","text":"сейчас у холма понять земле у него нет"},{"start":"627.089","dur":"4.261","text":"земли от океана до океана что ему кусок"},{"start":"629.67","dur":"5.909","text":"дали то его"},{"start":"631.35","dur":"10.2","text":"и вас всю украину сейчас гнуть на"},{"start":"635.579","dur":"9.271","text":"мировоззрение холопок вы носите сейчас"},{"start":"641.55","dur":"7.019","text":"вот именно холоп скими этими штампами"},{"start":"644.85","dur":"7.01","text":"вы не мыслите как казаки вам нельзя"},{"start":"648.569","dur":"3.291","text":"мыслить как казакам"},{"start":"653.01","dur":"5.86","text":"как раз сейчас у нас как раз в советский"},{"start":"656.38","dur":"6.36","text":"союз на мой взгляд и сделал из нас"},{"start":"658.87","dur":"6.18","text":"мировоззрение холопов а сейчас мы идем к"},{"start":"662.74","dur":"2.88","text":"вам я то что нужно осознать что это наша"},{"start":"665.05","dur":"4.05","text":"земля"},{"start":"665.62","dur":"8.76","text":"чтоб мы даже отстаивать интересы этого"},{"start":"669.1","dur":"8.609","text":"общества кто сделал савинский союз кто"},{"start":"674.38","dur":"7.11","text":"сделал большой и откуда взялись"},{"start":"677.709","dur":"8.761","text":"большевики кто сделал большевиков может"},{"start":"681.49","dur":"11.25","text":"быть там какие-то идеи какие то"},{"start":"686.47","dur":"11.669","text":"определенные кто сделал кто-то сделал"},{"start":"692.74","dur":"17.88","text":"большевиков кто утратил большевикам чтоб"},{"start":"698.139","dur":"14.101","text":"они были к к к к к к к я тайно вот вы"},{"start":"710.62","dur":"4.2","text":"вкурсе так что у вас голод был на"},{"start":"712.24","dur":"7.44","text":"украине до что приходили красные до"},{"start":"714.82","dur":"5.55","text":"забирали там продукты вот кто это сделал"},{"start":"719.68","dur":"7.31","text":"все с вами"},{"start":"720.37","dur":"6.62","text":"кто кто прислал красных вам кто"},{"start":"727.43","dur":"6.9","text":"я например понимаю я вижу это так"},{"start":"730.61","dur":"7.74","text":"понимаю это так что по сути дела как"},{"start":"734.33","dur":"8.73","text":"сказать большевистская власть вот кто"},{"start":"738.35","dur":"9.6","text":"прислал вам большевистскую власть кто-то"},{"start":"743.06","dur":"10.86","text":"красных прислав чтобы вы подъехали кто"},{"start":"747.95","dur":"8.52","text":"это сделал да да вот это и это я снова"},{"start":"753.92","dur":"5.37","text":"придет [ __ ] захватит россию захватит"},{"start":"756.47","dur":"4.77","text":"украину и будет вот такая хреновая жизнь"},{"start":"759.29","dur":"4.83","text":"будет все помирать кто это [ __ ] здесь"},{"start":"761.24","dur":"4.49","text":"сделал кто царя убил кто вот это вот все"},{"start":"764.12","dur":"5.43","text":"сделал"},{"start":"765.73","dur":"11.62","text":"чтобы мы погибали дохли помирали кто это"},{"start":"769.55","dur":"10.07","text":"сделал тут были люди которые плод"},{"start":"777.35","dur":"6.45","text":"платили"},{"start":"779.62","dur":"10.029","text":"вот госпереворот в российской империи"},{"start":"783.8","dur":"8.63","text":"сделали британцы грубо говоря"},{"start":"789.649","dur":"6.69","text":"посольством британии непосредственно"},{"start":"792.43","dur":"6.4","text":"устроила переворот в россии через"},{"start":"796.339","dur":"5.19","text":"поставки германские французские так"},{"start":"798.83","dur":"4.08","text":"далее это все осуществлялось британский"},{"start":"801.529","dur":"4.231","text":"экспедиционный корпус"},{"start":"802.91","dur":"6.42","text":"здесь мониторинг на месте осуществлял но"},{"start":"805.76","dur":"6.57","text":"перед этим они японию поставили то есть"},{"start":"809.33","dur":"6.69","text":"а британцы это вот есть британцы у них"},{"start":"812.33","dur":"7.98","text":"есть собака большая называется америка"},{"start":"816.02","dur":"8.22","text":"это их собака или дружную слом бреталь"},{"start":"820.31","dur":"6.69","text":"на вот они где раз вам надавали по морде"},{"start":"824.24","dur":"10.17","text":"нам надавали по морде заставили вас"},{"start":"827","dur":"10.2","text":"подохнуть нас подохнуть создали гусь"},{"start":"834.41","dur":"6.84","text":"переворот в российской империи в наши с"},{"start":"837.2","dur":"5.329","text":"вами империи убили нашего царя нашего с"},{"start":"841.25","dur":"4.86","text":"вами"},{"start":"842.529","dur":"5.281","text":"превратили нас в [ __ ] скотская которая"},{"start":"846.11","dur":"4.59","text":"подчинялась их менеджером"},{"start":"847.81","dur":"6.93","text":"коммунистическим вот ли они на трубке"},{"start":"850.7","dur":"7.23","text":"это их менеджеры которых прислали"},{"start":"854.74","dur":"5.199","text":"нагнули отымели по жесткому и вас у нас"},{"start":"857.93","dur":"5.219","text":"и всех"},{"start":"859.939","dur":"6.2","text":"прошло время на местах от имени же"},{"start":"863.149","dur":"9.35","text":"расслабились перестали слушать британцев"},{"start":"866.139","dur":"8.68","text":"их слона американцев пожили в каком то"},{"start":"872.499","dur":"4.15","text":"сразу было понятно что это гнилой"},{"start":"874.819","dur":"8.6","text":"проекты римский целью что он все равно"},{"start":"876.649","dur":"6.77","text":"когда-то развалится они заранее сделали"},{"start":"883.689","dur":"5.41","text":"все что был когда когда разваливался"},{"start":"886.819","dur":"5.31","text":"чтобы было все правильно они придумали"},{"start":"889.099","dur":"5.06","text":"вот это вот убрали малороссов и"},{"start":"892.129","dur":"2.03","text":"белорусов"},{"start":"894.489","dur":"8.2","text":"великороссов и вели понятие русский"},{"start":"897.879","dur":"7.3","text":"назвали великороссов русским них с этого"},{"start":"902.689","dur":"4.531","text":"момента украинцы пиль малороссы"},{"start":"905.179","dur":"5.34","text":"перестали быть русскими белорусы"},{"start":"907.22","dur":"6.239","text":"перестали быть русскими то есть развели"},{"start":"910.519","dur":"18.93","text":"как лохов придумали название подменили"},{"start":"913.459","dur":"20.04","text":"термин российской империи нет великоросс"},{"start":"929.449","dur":"7.11","text":"рима лагу это естественно названием ваши"},{"start":"933.499","dur":"10.83","text":"дед называли себя мало русами потому что"},{"start":"936.559","dur":"18.06","text":"вы в малороссии живет вот вам и там были"},{"start":"944.329","dur":"14.1","text":"левушка вам это навтыкали веруйте метод"},{"start":"954.619","dur":"7.02","text":"показа и да об этом отдельно подумаете в"},{"start":"958.429","dur":"6.51","text":"отличаться ушли от этого вот с того"},{"start":"961.639","dur":"7.47","text":"момента как малоросс перестал быть"},{"start":"964.939","dur":"6.39","text":"мороза моста украинцам ему нельзя теперь"},{"start":"969.109","dur":"4.76","text":"помни что он русский украинец это"},{"start":"971.329","dur":"2.54","text":"русский"},{"start":"979.96","dur":"18.37","text":"я есть смешанные"},{"start":"995.18","dur":"3.15","text":"[музыка]"},{"start":"1008.18","dur":"30.99","text":"[музыка]"},{"start":"1009.26","dur":"29.91","text":"серия фильмов российский могу так долго"},{"start":"1065.78","dur":"5.56","text":"все вы погнали балду вы не можете"},{"start":"1068.85","dur":"5.22","text":"сосредоточиться я понял вы передаете"},{"start":"1071.34","dur":"5.55","text":"эмоции ваши мироощущения а есть"},{"start":"1074.07","dur":"5.19","text":"информации логика вы про логику вот я"},{"start":"1076.89","dur":"6.23","text":"вам сказал в чем логика заключается а вы"},{"start":"1079.26","dur":"14.64","text":"сейчас про эмоцию и про мироощущения"},{"start":"1083.12","dur":"13.74","text":"было название малороссы вот у вас было"},{"start":"1093.9","dur":"2.96","text":"национальность русский"},{"start":"1097.72","dur":"12","text":"она была вы были три русских народа это"},{"start":"1107.34","dur":"12.72","text":"переселение вас обманули не было"},{"start":"1109.72","dur":"12.75","text":"переселено по советскому союзу бываю на"},{"start":"1120.06","dur":"4.66","text":"метался народ по советскому союзу"},{"start":"1122.47","dur":"17.78","text":"направляю туда-сюда и чё как на"},{"start":"1124.72","dur":"17.78","text":"переселение влияние телевизора и"},{"start":"1140.25","dur":"9.4","text":"зомбированного этого потока"},{"start":"1142.5","dur":"10.95","text":"все ну там действительно профессионально"},{"start":"1149.65","dur":"19.5","text":"телевизоре маленькая посмотрел работает"},{"start":"1153.45","dur":"17.92","text":"работает на необитаемый остров и вот"},{"start":"1169.15","dur":"5.54","text":"сейчас британцы вас отрабатывают как"},{"start":"1171.37","dur":"6.3","text":"прошлый раз мы сейчас"},{"start":"1174.69","dur":"6.1","text":"отрабатывайте с британцами точно так же"},{"start":"1177.67","dur":"5.88","text":"как один раз мы были лахами теперь мы"},{"start":"1180.79","dur":"5.4","text":"второй раз ллахи кстати трети уже или"},{"start":"1183.55","dur":"6.47","text":"какой там 8 может быть раз мы все"},{"start":"1186.19","dur":"3.83","text":"работаем блохами для британцев"},{"start":"1198.919","dur":"7.44","text":"то что вы описываете что вы оба эти"},{"start":"1202.039","dur":"6.57","text":"земли круга я постараюсь набегов вы что"},{"start":"1206.359","dur":"6.18","text":"имеете ввиду под татарами монголами"},{"start":"1208.609","dur":"6.78","text":"что были какие-то татаро-монголы ребятам"},{"start":"1212.539","dur":"5.911","text":"было это кто такие это какие-то люди"},{"start":"1215.389","dur":"9.961","text":"какой-то национальности или это опять"},{"start":"1218.45","dur":"9.15","text":"малороссы великороссы не было здесь"},{"start":"1225.35","dur":"4.159","text":"никакой другой национальности справочно"},{"start":"1227.6","dur":"5.039","text":"вот вот это осознаете"},{"start":"1229.509","dur":"6.071","text":"другой национальности не было вы не"},{"start":"1232.639","dur":"6.15","text":"понимаете чтоб хоть и творится открыть и"},{"start":"1235.58","dur":"10.579","text":"никого круче малороссов великороссов"},{"start":"1238.789","dur":"9.96","text":"белорусов поляков никого не было это"},{"start":"1246.159","dur":"4.47","text":"подмена терминов вот как великороссов"},{"start":"1248.749","dur":"9.201","text":"подменили с русскими так и"},{"start":"1250.629","dur":"12.13","text":"татаро-монголов это воинское образование"},{"start":"1257.95","dur":"8.709","text":"мы жили на этих территориях извечно этом"},{"start":"1262.759","dur":"6.36","text":"и татаро-монгол и вы сахара монголы это"},{"start":"1266.659","dur":"15.99","text":"наша между собой туса которая здесь"},{"start":"1269.119","dur":"16.31","text":"водится все потому что британская вот"},{"start":"1282.649","dur":"6.081","text":"это против таро ты тогда работал"},{"start":"1285.429","dur":"15.551","text":"билляхи тогда уже были отработаны"},{"start":"1288.73","dur":"16.569","text":"католичеству что должен делать туземец"},{"start":"1300.98","dur":"7.62","text":"вот вы туземцы мы должны друг другу"},{"start":"1305.299","dur":"5.161","text":"отгрызать голову не важно кто либо пай -"},{"start":"1308.6","dur":"5.48","text":"с поляками"},{"start":"1310.46","dur":"8.669","text":"должны собачиться либо со шведами"},{"start":"1314.08","dur":"8.409","text":"собачиться мы должны просто друг друга"},{"start":"1319.129","dur":"6.091","text":"грызть чтобы мы не шли на запад и на юг"},{"start":"1322.489","dur":"6.491","text":"потому что когда мы друг друга не грозил"},{"start":"1325.22","dur":"7.87","text":"мы собираемся в одно войско и тогда"},{"start":"1328.98","dur":"7.069","text":"раз наступает всем того чтобы мы в одном"},{"start":"1333.09","dur":"8.13","text":"близко не собирались нас посыпают"},{"start":"1336.049","dur":"10.691","text":"информация my всякими дурацкими слухи"},{"start":"1341.22","dur":"7.949","text":"пускают что угодно делать но вот там"},{"start":"1346.74","dur":"6.15","text":"гаснет лжедмитрия впускают чё угодно"},{"start":"1349.169","dur":"5.731","text":"лишь бы мы между собой грызлись и друг"},{"start":"1352.89","dur":"4.98","text":"друга резали отгрызали себе голову все"},{"start":"1354.9","dur":"6.3","text":"это старо как мир и на как лохи это"},{"start":"1357.87","dur":"7.14","text":"исполняем и сейчас следующая серия мы"},{"start":"1361.2","dur":"6.75","text":"лохи мы сами себя убиваем вот когда"},{"start":"1365.01","dur":"5.1","text":"малороссы убивает welicoruss это два"},{"start":"1367.95","dur":"4.349","text":"русских народов пеликана великоросс"},{"start":"1370.11","dur":"5.25","text":"собирает малороссов это два русских"},{"start":"1372.299","dur":"9.531","text":"народов это мы сами себя убиваем на"},{"start":"1375.36","dur":"6.47","text":"потеху тому кто платит бритта но и да"},{"start":"1385.64","dur":"42.909","text":"можно развести легко историю украсть"},{"start":"1392.76","dur":"40.08","text":"мышление вы будете это земля тема чем у"},{"start":"1428.549","dur":"9.031","text":"земли жили соседи ночей земле"},{"start":"1432.84","dur":"7.219","text":"пути квартиры это вообще колодки или"},{"start":"1437.58","dur":"2.479","text":"казачьи"},{"start":"1447.67","dur":"6.94","text":"палятся ну хорошо дальше дальше то виду"},{"start":"1451.67","dur":"4.29","text":"вот-вот живем и как соседи дальше чем вы"},{"start":"1454.61","dur":"4.71","text":"подписали бумагу"},{"start":"1455.96","dur":"6.33","text":"написали что вам переходит площадка"},{"start":"1459.32","dur":"6.06","text":"балкон и лоджия если вы будете вести"},{"start":"1462.29","dur":"5.99","text":"себя как [ __ ] вот если вы не будете"},{"start":"1465.38","dur":"7.82","text":"вести себя как было можете пользоваться"},{"start":"1468.28","dur":"9.94","text":"корриган вы подписали такую бумагу"},{"start":"1473.2","dur":"7.45","text":"балконом пользуйтесь в переводе на"},{"start":"1478.22","dur":"5.73","text":"русский язык вы написали если вы будете"},{"start":"1480.65","dur":"5.37","text":"там какой статус нейтральный статус"},{"start":"1483.95","dur":"7.34","text":"облёк соблюдают тут она пользуетесь"},{"start":"1486.02","dur":"6.48","text":"этими территориями потому что вошли в"},{"start":"1491.29","dur":"5.71","text":"империю"},{"start":"1492.5","dur":"6.84","text":"или советский союз как угодно не на той"},{"start":"1497","dur":"12.45","text":"земле с которой вы вышли поэтому мы"},{"start":"1499.34","dur":"14.58","text":"подписали бумагу оккупировал вы сами"},{"start":"1509.45","dur":"17.43","text":"себя оккупировали что как могла сама"},{"start":"1513.92","dur":"15.509","text":"себя оккупировать российской империи это"},{"start":"1526.88","dur":"9.09","text":"были междуусобицы до московского царства"},{"start":"1529.429","dur":"8.611","text":"чтобы был шанс philos хана тела ходил"},{"start":"1535.97","dur":"5.39","text":"вот канал там огибала рим и то что было"},{"start":"1538.04","dur":"8.85","text":"это было до московского царства"},{"start":"1541.36","dur":"10.319","text":"это все та же самая туса была туса туса"},{"start":"1546.89","dur":"4.789","text":"то же самое тот же самый народ"},{"start":"1561.39","dur":"3.089","text":"[музыка]"},{"start":"1565.12","dur":"6.24","text":"вы про юридический фактор ванной"},{"start":"1568.36","dur":"5.22","text":"считается вашей землей в рамках договора"},{"start":"1571.36","dur":"7.05","text":"что если вы не будете вести себя как"},{"start":"1573.58","dur":"7.229","text":"[ __ ] а вы когда выходили советского"},{"start":"1578.41","dur":"6.87","text":"союза выйти рамки подписали написали"},{"start":"1580.809","dur":"6.871","text":"если мы не будем вести себя как [ __ ] то"},{"start":"1585.28","dur":"7.32","text":"тогда нам принадлежат вот это вот это"},{"start":"1587.68","dur":"7.95","text":"вот это балкон коридор и лучше вторая"},{"start":"1592.6","dur":"13.41","text":"сторона да и хрен с ним подписала пусть"},{"start":"1595.63","dur":"13.77","text":"так потому что видно"},{"start":"1606.01","dur":"6.21","text":"подписали договор вы вы захватили чужую"},{"start":"1609.4","dur":"4.909","text":"землю с собой потащили как чакры"},{"start":"1612.22","dur":"8.97","text":"потащили"},{"start":"1614.309","dur":"9.731","text":"донбасса тащили кучу потащили советский"},{"start":"1621.19","dur":"6.39","text":"союз с этими землями нет почему вы"},{"start":"1624.04","dur":"5.55","text":"ходите вы пришли по сидели на стуле и"},{"start":"1627.58","dur":"13.229","text":"повалили дальше на хрена над собой взяли"},{"start":"1629.59","dur":"12.839","text":"телевизор взяли диван зачем вы сейчас"},{"start":"1640.809","dur":"3.661","text":"говорите про выход из советского союза"},{"start":"1642.429","dur":"8.571","text":"формирование у коренных оконечного"},{"start":"1644.47","dur":"10.47","text":"государства когда он был тьму тараканью"},{"start":"1651","dur":"8.13","text":"дарили это была единая земля вот этого"},{"start":"1654.94","dur":"14.54","text":"всего кодла которого которая проживала"},{"start":"1659.13","dur":"10.35","text":"совокупность лучших народов или были бы"},{"start":"1670.2","dur":"6.96","text":"оттуда скифы вот скифы это вот как раз"},{"start":"1676.02","dur":"7.29","text":"тут самый народ"},{"start":"1677.16","dur":"9.27","text":"которые в китае скифы и украину слышал"},{"start":"1683.31","dur":"5.33","text":"паранджу русскую вы можете в китае на"},{"start":"1686.43","dur":"4.89","text":"севере китая"},{"start":"1688.64","dur":"5.32","text":"китайцы запрещают это раскопать туда"},{"start":"1691.32","dur":"7.46","text":"впал помогут этой скифской культуры с"},{"start":"1693.96","dur":"4.82","text":"русскими орнаментами с вышиванками и"},{"start":"1703.55","dur":"14.62","text":"украинцы то скифи завоевать все"},{"start":"1715.89","dur":"6.18","text":"понимаете несуществующая информация там"},{"start":"1718.17","dur":"6.54","text":"же народ у него были такие правления"},{"start":"1722.07","dur":"5.73","text":"такие междусобойчики так далее но это"},{"start":"1724.71","dur":"6.72","text":"был один и тот же народ вот человек"},{"start":"1727.8","dur":"5.76","text":"живший жившие на запорожье"},{"start":"1731.43","dur":"15.11","text":"он ничем не отличался от человека в"},{"start":"1733.56","dur":"12.98","text":"рязани понимаете указывать британцы"},{"start":"1750.02","dur":"5.98","text":"британцы сделали развал советского"},{"start":"1752.75","dur":"5.71","text":"развал российской империи а дальше все"},{"start":"1756","dur":"5.43","text":"прочитала споймает это все просто вы"},{"start":"1758.46","dur":"5.67","text":"даете батлу идею [ __ ] начинает себя"},{"start":"1761.43","dur":"4.86","text":"убивать сама себя вгрызаться земцы вот"},{"start":"1764.13","dur":"4.53","text":"эти вот мы с вами начинаем сами себя"},{"start":"1766.29","dur":"3.87","text":"убивать это понятно мы до этим коммунизм"},{"start":"1768.66","dur":"4.83","text":"это понятно что они там сколько-то лет"},{"start":"1770.16","dur":"6.54","text":"по буксуют и разваливаться а чтоб они"},{"start":"1773.49","dur":"6.5","text":"разваливались мы дадим им за саму чтобы"},{"start":"1776.7","dur":"6.06","text":"у нас сам вот эти вот менеджер на местах"},{"start":"1779.99","dur":"6.63","text":"взращивали украинскую национальность"},{"start":"1782.76","dur":"5.88","text":"отдельно взращивали белорусов отдельно"},{"start":"1786.62","dur":"5.68","text":"взращивали все хоть"},{"start":"1788.64","dur":"5.55","text":"сильно изменит жили британские на местах"},{"start":"1792.3","dur":"4.2","text":"советском союзе первое что начали делать"},{"start":"1794.19","dur":"21.87","text":"они закладывали фундамент будущего"},{"start":"1796.5","dur":"22.86","text":"развала было беззаконное действие на"},{"start":"1816.06","dur":"5.99","text":"местах люди не имеющие полномочий"},{"start":"1819.36","dur":"5.57","text":"составили бумаж"},{"start":"1822.05","dur":"7","text":"незаконную вот выход украины"},{"start":"1824.93","dur":"5.65","text":"он незаконен распад союза он незаконен"},{"start":"1829.05","dur":"5.69","text":"потому что был референдум на котором"},{"start":"1830.58","dur":"4.16","text":"решили никто никуда не выходит"},{"start":"1839.9","dur":"4.51","text":"беззаконное действие на местах"},{"start":"1842.15","dur":"4.81","text":"состоявшая бумажку ну хрен с ним мы"},{"start":"1844.41","dur":"3.18","text":"считаем ее что надо ее придерживаться к"},{"start":"1846.96","dur":"3.36","text":"бумажке"},{"start":"1847.59","dur":"7.47","text":"бумажки что-то написано мы читаем что"},{"start":"1850.32","dur":"6.99","text":"написано написано если украина не будет"},{"start":"1855.06","dur":"6.53","text":"вести себя как было она может"},{"start":"1857.31","dur":"4.28","text":"пользоваться вот этими территориями все"},{"start":"1869.17","dur":"6.26","text":"[музыка]"},{"start":"1872.15","dur":"7.06","text":"вот вот вот хрущев не мог подарить"},{"start":"1875.43","dur":"7.47","text":"ничего никому потому что это не имеет"},{"start":"1879.21","dur":"5.76","text":"права какая-то овца manage британский на"},{"start":"1882.9","dur":"5.48","text":"территории бывшей российской империи"},{"start":"1884.97","dur":"5.79","text":"давить территории потому что народ"},{"start":"1888.38","dur":"4.69","text":"населяющие ты территории не является"},{"start":"1890.76","dur":"6.62","text":"скотом что того какая то бы для чая"},{"start":"1893.07","dur":"7.56","text":"хрущеве на дарила не важно кому"},{"start":"1897.38","dur":"6.18","text":"отдала от россии туда то вот они не"},{"start":"1900.63","dur":"5.67","text":"являются скотом чтобы их дарить и"},{"start":"1903.56","dur":"6.04","text":"считать вот это вот законным актом нет"},{"start":"1906.3","dur":"8.87","text":"никаких оснований [ __ ] не имеет права"},{"start":"1909.6","dur":"5.57","text":"дарить людей не являющихся скотом"},{"start":"1919.429","dur":"4.591","text":"российской империи британцами все"},{"start":"1927.19","dur":"3.21","text":"[музыка]"},{"start":"1952.279","dur":"5.951","text":"представители законной власти вот эта"},{"start":"1955.529","dur":"4.051","text":"власть вот полностью советского союза"},{"start":"1958.23","dur":"13.38","text":"она незаконная"},{"start":"1959.58","dur":"14.91","text":"от самого начала до самого конца это по"},{"start":"1971.61","dur":"6.12","text":"барабану согласно она не согласна схема"},{"start":"1974.49","dur":"6.09","text":"работает не таким образом создается"},{"start":"1977.73","dur":"7.53","text":"схема чтобы [ __ ] туземцы друг сами себя"},{"start":"1980.58","dur":"7.02","text":"к убивали и создается схема под это"},{"start":"1985.26","dur":"3.659","text":"информационное [ __ ] начинает сама себя"},{"start":"1987.6","dur":"5.01","text":"убивать все"},{"start":"1988.919","dur":"6.961","text":"а дальше это уже подробности эти"},{"start":"1992.61","dur":"6.87","text":"подробности надо усиливать так далее так"},{"start":"1995.88","dur":"6","text":"прочие делать учатся надо чтобы [ __ ]"},{"start":"1999.48","dur":"6.049","text":"убивала себя дальше разделить церковь"},{"start":"2001.88","dur":"8.25","text":"православную дать тоже британский проект"},{"start":"2005.529","dur":"7.831","text":"это чисто британцы месяц религию делят"},{"start":"2010.13","dur":"12.179","text":"чтобы мы и дальше себе убивали"},{"start":"2013.36","dur":"13.89","text":"все все просто лохи понятно в сел у-2 ти"},{"start":"2022.309","dur":"11.901","text":"как вам угодно наслаждайтесь моментом"},{"start":"2027.25","dur":"6.96","text":"мыслите и мыслями о переселении народов"},{"start":"2035.02","dur":"8.72","text":"вот чё угодно творите"},{"start":"2037.48","dur":"6.26","text":"я устал уже мне хватит на другие вопросы"},{"start":"2050.28","dur":"5.849","text":"извините извините за слово"}]